cameracommander/__init__.py
cameracommander/camera.py
cameracommander/cli.py
cameracommander/py.typed
cameracommander/settings.py
cameracommander-0.1.1.dist-info/METADATA
cameracommander-0.1.1.dist-info/WHEEL
cameracommander-0.1.1.dist-info/entry_points.txt
cameracommander-0.1.1.dist-info/licenses/LICENSE
cameracommander-0.1.1.dist-info/RECORD
