Metadata-Version: 2.3
Name: cameracommander
Version: 0.1.1
Summary: Add your description here
License-File: LICENSE
Requires-Python: >=3.11
Requires-Dist: click>=8.1.7
Requires-Dist: gphoto2>=2.5.0
Requires-Dist: pyyaml>=6.0.2
Requires-Dist: ruff>=0.6.7
